setup.py
pythontree/__init__.py
pythontree.egg-info/PKG-INFO
pythontree.egg-info/SOURCES.txt
pythontree.egg-info/dependency_links.txt
pythontree.egg-info/top_level.txt