Metadata-Version: 1.1
Name: pythontree
Version: 1.5.3
Summary: facilitate folder management
Home-page: https://github.com/MattVoid/pythontree
Author: MattVoid
Author-email: am.monteleone.am@gmail.com
License: Apache-2.0
Platform: UNKNOWN
Classifier: Development Status :: 4 - Beta
